seito-0.2.6.dist-info/METADATA
seito-0.2.6.dist-info/WHEEL
seito/__init__.py
seito/http.py
seito/json.py
seito/monad/__init__.py
seito/monad/async_result.py
seito/monad/container.py
seito/monad/effect.py
seito/monad/func.py
seito/monad/option.py
seito/monad/result.py
seito/py.typed.py
seito-0.2.6.dist-info/RECORD
