Metadata-Version: 2.1
Name: seito
Version: 0.2.6
Summary: rusty container
Author-Email: Marco <cram@hotmail.fr>
License: MIT
Requires-Python: >=3.10
Requires-Dist: aiohttp>=3.8.4
Requires-Dist: pampy>=0.3.0
